waldur_slurm/__init__.py
waldur_slurm/admin.py
waldur_slurm/apps.py
waldur_slurm/backend.py
waldur_slurm/client.py
waldur_slurm/executors.py
waldur_slurm/extension.py
waldur_slurm/filters.py
waldur_slurm/handlers.py
waldur_slurm/models.py
waldur_slurm/serializers.py
waldur_slurm/tasks.py
waldur_slurm/urls.py
waldur_slurm/utils.py
waldur_slurm/views.py
waldur_slurm/migrations/0001_initial.py
waldur_slurm/migrations/0002_add_gpu_ram_quotas.py
waldur_slurm/migrations/__init__.py
waldur_slurm/tests/__init__.py
waldur_slurm/tests/factories.py
waldur_slurm/tests/fixtures.py
waldur_slurm/tests/test_backend.py
waldur_slurm/tests/test_quotas.py
waldur_slurm-0.1.3.dist-info/DESCRIPTION.rst
waldur_slurm-0.1.3.dist-info/METADATA
waldur_slurm-0.1.3.dist-info/RECORD
waldur_slurm-0.1.3.dist-info/WHEEL
waldur_slurm-0.1.3.dist-info/entry_points.txt
waldur_slurm-0.1.3.dist-info/metadata.json
waldur_slurm-0.1.3.dist-info/top_level.txt
