Metadata-Version: 2.0
Name: waldur-slurm
Version: 0.1.3
Summary: Waldur plugin for SLURM accounting synchronization.
Home-page: http://waldur.com
Author: OpenNode Team
Author-email: info@opennodecloud.com
License: MIT
Platform: UNKNOWN
Classifier: Framework :: Django
Classifier: Intended Audience :: Developers
Classifier: Intended Audience :: System Administrators
Classifier: Operating System :: OS Independent
Classifier: License :: OSI Approved :: MIT License
Requires-Dist: nodeconductor (>=0.145.5)
Requires-Dist: waldur-freeipa (>=0.2.2)
Provides-Extra: tests
Requires-Dist: ddt (<1.1.0,>=1.0.0); extra == 'tests'
Requires-Dist: factory-boy (==2.4.1); extra == 'tests'
Requires-Dist: freezegun (==0.3.7); extra == 'tests'
Requires-Dist: mock (>=1.0.1); extra == 'tests'
Requires-Dist: mock-django (==0.6.9); extra == 'tests'
Requires-Dist: six (>=1.9.0); extra == 'tests'
Requires-Dist: sqlalchemy (>=1.0.12); extra == 'tests'
